turkic_translit/__init__.py
turkic_translit/cli.py
turkic_translit/core.py
turkic_translit/error_service.py
turkic_translit/lang_filter.py
turkic_translit/lang_utils.py
turkic_translit/langid.py
turkic_translit/logging_config.py
turkic_translit/model_utils.py
turkic_translit/patches.py
turkic_translit/pipeline.py
turkic_translit/sanity.py
turkic_translit/tokenizer.py
turkic_translit/transliterate.py
turkic_translit/cli/__init__.py
turkic_translit/cli/_net_utils.py
turkic_translit/cli/build_spm.py
turkic_translit/cli/corpora.yaml
turkic_translit/cli/download_corpus.py
turkic_translit/cli/eval_lm.py
turkic_translit/cli/filter_russian.py
turkic_translit/cli/pyicu_install.py
turkic_translit/cli/run_leven.py
turkic_translit/cli/train_lm.py
turkic_translit/cli/train_spm.py
turkic_translit/lm/__init__.py
turkic_translit/lm/data.py
turkic_translit/lm/eval.py
turkic_translit/lm/similarity.py
turkic_translit/lm/tokenizer.py
turkic_translit/lm/train.py
turkic_translit/rules/ar_lat.rules
turkic_translit/rules/az_ipa.rules
turkic_translit/rules/fi_ipa.rules
turkic_translit/rules/kk_ipa.rules
turkic_translit/rules/kk_lat.rules
turkic_translit/rules/ky_ipa.rules
turkic_translit/rules/ky_lat.rules
turkic_translit/rules/tr_ipa.rules
turkic_translit/rules/tr_lat.rules
turkic_translit/rules/ug_ipa.rules
turkic_translit/rules/uz_ipa.rules
turkic_translit/rules/uzc_ipa.rules
turkic_translit/web/__init__.py
turkic_translit/web/web_demo.py
turkic_translit/web/web_utils.py
turkic_translit/web/tabs/__init__.py
turkic_translit/web/tabs/corpus.py
turkic_translit/web/tabs/direct.py
turkic_translit/web/tabs/mutual.py
turkic_translit/web/tabs/sentencepiece.py
turkic_translit-0.3.6.dist-info/licenses/LICENSE
turkic_translit-0.3.6.dist-info/METADATA
turkic_translit-0.3.6.dist-info/WHEEL
turkic_translit-0.3.6.dist-info/entry_points.txt
turkic_translit-0.3.6.dist-info/top_level.txt
turkic_translit-0.3.6.dist-info/RECORD
