Metadata-Version: 2.4
Name: turkic-translit
Version: 0.3.6
Summary: Deterministic Latin and IPA transliteration for Kazakh, Kyrgyz, Uzbek, Turkish, Azerbaijani, Uyghur, Finnish, plus tokenizer/glue scripts.
Author-email: Austin Wagner <austinwagner@msn.com>
License-Expression: MIT
Keywords: kazakh,kyrgyz,transliteration,ipa
Classifier: Programming Language :: Python :: 3
Classifier: Programming Language :: Python :: 3.10
Classifier: Programming Language :: Python :: 3.11
Classifier: Programming Language :: Python :: 3.12
Classifier: Programming Language :: Python :: 3.13
Classifier: Operating System :: OS Independent
Classifier: Intended Audience :: Developers
Classifier: Intended Audience :: Science/Research
Classifier: Topic :: Software Development :: Libraries
Classifier: Topic :: Text Processing :: Linguistic
Requires-Python: >=3.9
License-File: LICENSE
Requires-Dist: epitran<1.27,>=1.0
Requires-Dist: fasttext-wheel==0.9.2
Requires-Dist: numpy<2
Requires-Dist: packaging>=23.0
Requires-Dist: panphon<0.22,>=0.20
Requires-Dist: PyICU<2.16,>=2.13; sys_platform != "win32"
Requires-Dist: pytest>=8.0
Requires-Dist: rapidfuzz>=3.5
Requires-Dist: rich>=13.7
Requires-Dist: python-json-logger>=2.0.4
Requires-Dist: sentencepiece>=0.2.0
Requires-Dist: click>=8.1
Requires-Dist: types-requests>=2.31
Requires-Dist: datasets<4.0.0,>=3.6.0
Requires-Dist: evaluate>=0.4
Requires-Dist: accelerate>=0.28
Requires-Dist: transformers<5,>=4.41
Requires-Dist: tqdm>=4.66
Requires-Dist: scikit-learn>=1.4
Requires-Dist: typing_extensions>=4.12
Requires-Dist: wikipedia<2.0.0,>=1.4.0
Requires-Dist: gradio>=4.0
Requires-Dist: pandas
Requires-Dist: matplotlib>=3.9
Requires-Dist: pycountry>=23.12
Requires-Dist: zstandard>=0.23
Provides-Extra: examples
Requires-Dist: flask; extra == "examples"
Requires-Dist: streamlit; extra == "examples"
Requires-Dist: jupyterlab; extra == "examples"
Provides-Extra: winlid
Provides-Extra: corpus
Requires-Dist: datasets>=3.0; extra == "corpus"
Requires-Dist: pyarrow>=14.0; extra == "corpus"
Requires-Dist: requests>=2.0; extra == "corpus"
Provides-Extra: sentry
Requires-Dist: sentry-sdk>=2.0; extra == "sentry"
Provides-Extra: dev
Requires-Dist: ruff>=0.2.0; extra == "dev"
Requires-Dist: mypy>=1.0; extra == "dev"
Requires-Dist: pytest>=8.0; extra == "dev"
Requires-Dist: build>=1.0; extra == "dev"
Requires-Dist: twine>=4.0; extra == "dev"
Requires-Dist: make>=0.1.6; extra == "dev"
Requires-Dist: types-requests>=2.31; extra == "dev"
Dynamic: license-file
